odoo9_addon_l10n_es_partner_mercantil-9.0.1.0.0-py2.7-nspkg.pth
odoo9_addon_l10n_es_partner_mercantil-9.0.1.0.0.dist-info/top_level.txt
odoo9_addon_l10n_es_partner_mercantil-9.0.1.0.0.dist-info/WHEEL
odoo9_addon_l10n_es_partner_mercantil-9.0.1.0.0.dist-info/RECORD
odoo9_addon_l10n_es_partner_mercantil-9.0.1.0.0.dist-info/metadata.json
odoo9_addon_l10n_es_partner_mercantil-9.0.1.0.0.dist-info/DESCRIPTION.rst
odoo9_addon_l10n_es_partner_mercantil-9.0.1.0.0.dist-info/METADATA
odoo9_addon_l10n_es_partner_mercantil-9.0.1.0.0.dist-info/namespace_packages.txt
odoo_addons/l10n_es_partner_mercantil/__openerp__.py
odoo_addons/l10n_es_partner_mercantil/__init__.py
odoo_addons/l10n_es_partner_mercantil/README.rst
odoo_addons/l10n_es_partner_mercantil/models/__init__.py
odoo_addons/l10n_es_partner_mercantil/models/partner_es.py
odoo_addons/l10n_es_partner_mercantil/i18n/pt.po
odoo_addons/l10n_es_partner_mercantil/i18n/es.po
odoo_addons/l10n_es_partner_mercantil/i18n/hr.po
odoo_addons/l10n_es_partner_mercantil/i18n/bg.po
odoo_addons/l10n_es_partner_mercantil/i18n/gl.po
odoo_addons/l10n_es_partner_mercantil/i18n/ca.po
odoo_addons/l10n_es_partner_mercantil/i18n/sl.po
odoo_addons/l10n_es_partner_mercantil/i18n/l10n_es_partner_mercantil.pot
odoo_addons/l10n_es_partner_mercantil/i18n/nl.po
odoo_addons/l10n_es_partner_mercantil/i18n/fr.po
odoo_addons/l10n_es_partner_mercantil/i18n/pt_BR.po
odoo_addons/l10n_es_partner_mercantil/views/res_partner_view.xml
odoo_addons/l10n_es_partner_mercantil/static/description/icon.svg
odoo_addons/l10n_es_partner_mercantil/static/description/icon.png
