Metadata-Version: 2.0
Name: odoo9-addon-l10n-es-partner-mercantil
Version: 9.0.1.0.0
Summary: Añade los datos del registro mercantil a la empresa
Home-page: https://odoo-community.org/
Author: Spanish Localization Team, Tecnativa, Odoo Community Association (OCA)
Author-email: support@odoo-community.org
License: AGPL-3
Platform: UNKNOWN
Requires-Dist: odoo (<9.1a,>=9.0a)
Classifier: Programming Language :: Python :: 2.7
Classifier: Framework :: Odoo
Classifier: License :: OSI Approved :: GNU Affero General Public License v3
